pydanticutils/__init__.py
pydanticutils/yaml.py
pydanticutils-0.0.3.dist-info/LICENSE
pydanticutils-0.0.3.dist-info/METADATA
pydanticutils-0.0.3.dist-info/WHEEL
pydanticutils-0.0.3.dist-info/top_level.txt
pydanticutils-0.0.3.dist-info/RECORD
